<mujocoinclude>
  <asset>
    <mesh name="base_link_0" file="base_link_0.stl"/>
    <mesh name="base_link_1" file="base_link_1.stl"/>
    <mesh name="base_link_2" file="base_link_2.stl"/>
    <mesh name="base_link_3" file="base_link_3.stl"/>
    <mesh name="base_link_4" file="base_link_4.stl"/>
    <mesh name="base_link_5" file="base_link_5.stl"/>
    <mesh name="base_link_6" file="base_link_6.stl"/>
    <mesh name="base_link_7" file="base_link_7.stl"/>
    <mesh name="base_link_8" file="base_link_8.stl"/>
    <mesh name="base_link_9" file="base_link_9.stl"/>
    <mesh name="base_link_10" file="base_link_10.stl"/>
    <mesh name="base_link_11" file="base_link_11.stl"/>
    <mesh name="base_link_12" file="base_link_12.stl"/>
    <mesh name="base_link_13" file="base_link_13.stl"/>
    <mesh name="base_link_14" file="base_link_14.stl"/>
    <mesh name="base_link_15" file="base_link_15.stl"/>
    <mesh name="base_link_16" file="base_link_16.stl"/>
    <mesh name="base_link_17" file="base_link_17.stl"/>
    <mesh name="base_link_18" file="base_link_18.stl"/>
    <mesh name="base_link_19" file="base_link_19.stl"/>
    <mesh name="base_link_20" file="base_link_20.stl"/>
    <mesh name="base_link_21" file="base_link_21.stl"/>
    <mesh name="base_link_22" file="base_link_22.stl"/>
    <mesh name="base_link_23" file="base_link_23.stl"/>
    <mesh name="base_link_24" file="base_link_24.stl"/>
    <mesh name="base_link_25" file="base_link_25.stl"/>
    <mesh name="base_link_26" file="base_link_26.stl"/>
    <mesh name="base_link_27" file="base_link_27.stl"/>
    <mesh name="base_link_28" file="base_link_28.stl"/>
    <mesh name="base_link_29" file="base_link_29.stl"/>
    <mesh name="base_link_30" file="base_link_30.stl"/>
    <mesh name="base_link_31" file="base_link_31.stl"/>
    <mesh name="base_link_32" file="base_link_32.stl"/>
    <mesh name="base_link_33" file="base_link_33.stl"/>
    <mesh name="base_link_34" file="base_link_34.stl"/>
    <mesh name="base_link_35" file="base_link_35.stl"/>
    <mesh name="base_link_36" file="base_link_36.stl"/>
    <mesh name="base_link_37" file="base_link_37.stl"/>
    <mesh name="base_link_38" file="base_link_38.stl"/>
    <mesh name="base_link_39" file="base_link_39.stl"/>
    <mesh name="base_link_40" file="base_link_40.stl"/>
    <mesh name="base_link_41" file="base_link_41.stl"/>
    <mesh name="base_link_42" file="base_link_42.stl"/>
    <mesh name="base_link_43" file="base_link_43.stl"/>
    <mesh name="base_link_44" file="base_link_44.stl"/>
    <mesh name="base_link_45" file="base_link_45.stl"/>
    <mesh name="base_link_46" file="base_link_46.stl"/>
    <mesh name="base_link_47" file="base_link_47.stl"/>
    <mesh name="base_link_48" file="base_link_48.stl"/>
    <mesh name="base_link_49" file="base_link_49.stl"/>
    <mesh name="base_link_50" file="base_link_50.stl"/>
    <mesh name="base_link_51" file="base_link_51.stl"/>
    <mesh name="base_link_52" file="base_link_52.stl"/>
    <mesh name="base_link_53" file="base_link_53.stl"/>
    <mesh name="base_link_54" file="base_link_54.stl"/>
    <mesh name="base_link_55" file="base_link_55.stl"/>
    <mesh name="base_link_56" file="base_link_56.stl"/>
    <mesh name="base_link_57" file="base_link_57.stl"/>
    <mesh name="base_link_58" file="base_link_58.stl"/>
    <mesh name="base_link_59" file="base_link_59.stl"/>
    <mesh name="base_link_60" file="base_link_60.stl"/>
    <mesh name="base_link_61" file="base_link_61.stl"/>
    <mesh name="base_link_62" file="base_link_62.stl"/>
    <mesh name="base_link_63" file="base_link_63.stl"/>
  </asset>
</mujocoinclude>
