{
    "configurations": [
        {
            "name": "Linux",
            "includePath": [
                "${workspaceFolder}/sim_cpp/inc",
                "/usr/include/c++/11",
                "/usr/include/x86_64-linux-gnu/c++/11",
                "/usr/include/x86_64-linux-gnu",
                "~/Bags/mujoco-3.3.2/include",
                "/usr/include/eigen3"
            ],
            "defines": [],
            "compilerPath": "/usr/bin/clang-14",
            "cStandard": "c17",
            "cppStandard": "c++14",
            "intelliSenseMode": "linux-clang-x64"
        }
    ],
    "version": 4
}